{
  "사건번호": "2009다37886",
  "소송당사자": "원고(상고인), 피고(피상고인), 소외(제3자, 인재를 의뢰한 회사)",
  "소송 비용 청구": null,
  "전문 요약": "인재소개업체인 원고가 추천한 피고가 소외 회사와 입사 합의 후 취업의사를 철회하자, 원고는 피고에게 비즈니스 피해에 대한 손해배상을 청구했다. 원심은 원고의 손해액 입증 부족을 이유로 청구를 기각했으나, 대법원은 손해액 입증이 곤란한 경우 법원이 간접사실을 종합해 손해액을 산정할 수 있다고 보아 원심을 파기하고 환송했다.",
  "기초 사실": "원고는 인재소개업체로 소외 회사와 인력추천 계약을 맺고, 피고를 추천해 입사 합의가 이루어졌으나 피고가 입사를 철회했다.",
  "청구 취지": "원고는 피고의 입사 철회로 인해 소외 회사로부터 수수료를 받지 못한 손해에 대한 배상을 청구했다.",
  "원고 주장": "피고가 입사 합의 내용을 지키지 않아 원고가 소외 회사로부터 수수료를 받지 못하는 등 비즈니스 피해를 입었다고 주장했다.",
  "피고 주장": null,
  "소결론": "원심은 원고가 대체 인원을 추천하지 않았으므로 손해가 발생하지 않았다고 보았으나, 대법원은 대체 인원 추천 여부만으로 손해 발생을 단정할 수 없고, 손해액 산정이 곤란한 경우 법원이 간접사실을 종합해 판단해야 한다고 보았다.",
  "결론": "원심판결을 파기하고 사건을 다시 심리·판단하도록 환송했다."
}