{
  "사건번호": "2009다91828",
  "소송당사자": "원고(상고인), 피고(피상고인), 소외인(피고 등과 함께 기망행위에 가담한 제3자)",
  "소송 비용 청구": null,
  "전문 요약": "피고 등은 원고에게 부동산 매매와 관련해 허위사실로 기망하여 고가에 매수하게 했고, 원고는 실제 시가보다 비싸게 부동산을 매수했다. 원심은 이후 부동산 시가 상승과 보상금 수령 등으로 원고에게 손해가 없다고 판단했으나, 대법원은 불법행위로 인한 손해는 매수 당시 시가와 매수가격의 차액으로 산정해야 하며, 이후 시가 상승이나 보상금 수령은 손해 발생 여부에 영향을 주지 않는다고 보아 원심판결을 파기하고 환송했다.",
  "기초 사실": "피고 등은 원고에게 허위사실로 부동산을 고가에 매수하게 했고, 원고는 매매대금을 지급하고 소유권이전등기를 마쳤으며, 매매 당시 시가는 실제 매매가보다 낮았다. 이후 부동산 일부가 협의취득되어 보상금을 받았고, 부동산 시가가 상승했다.",
  "청구 취지": null,
  "원고 주장": null,
  "피고 주장": null,
  "소결론": "원심은 부동산 시가 상승과 보상금 수령 등으로 원고에게 손해가 없다고 판단했으나, 대법원은 손해는 매수 당시 시가와 매수가격의 차액으로 산정해야 한다고 보았다.",
  "결론": "원심판결을 파기하고 사건을 서울고등법원에 환송한다."
}