{
  "사건번호": "2010다53457",
  "소송당사자": "원고(상고인): 주식회사 한서플랜트, 피고(피상고인): 대한조선 주식회사",
  "소송 비용 청구": null,
  "전문 요약": "원고 한서플랜트가 피고 대한조선이 하도급대금을 부당하게 감액했다며 손해배상을 청구한 사건이다. 원심은 하도급법 위반만으로 정산합의의 사법상 효력이 무효가 아니라고 보아 원고의 청구를 기각했으나, 대법원은 하도급법 제11조 위반이 불법행위에 해당할 수 있으므로 원심이 이를 심리하지 않은 것은 위법이라 하여 해당 부분을 파기환송했다.",
  "기초 사실": "피고가 원고에게 하도급 공사대금을 지급하는 과정에서 정산합의를 통해 대금을 감액하였고, 공정거래위원회가 피고의 부당감액에 대해 시정명령을 내린 사실이 있다.",
  "청구 취지": "원고는 피고가 하도급대금을 부당하게 감액했다며 손해배상을 청구하였다.",
  "원고 주장": "피고가 우월적 지위를 이용해 자발적 동의 없이 하도급대금을 부당하게 감액하여 정산합의를 강요했고, 이는 하도급법 위반의 불법행위에 해당하므로 손해를 배상해야 한다고 주장했다.",
  "피고 주장": "정산합의는 유효하며, 하도급법 위반만으로 사법상 효력이 무효가 아니고, 불법행위도 성립하지 않는다고 주장했다.",
  "소결론": "원심은 하도급법 위반만으로 정산합의의 사법상 효력이 무효가 아니라고 보아 원고의 청구를 기각했다.",
  "결론": "대법원은 하도급대금 부당감액에 의한 손해배상청구 부분을 파기하고 환송하며, 나머지 상고는 기각했다."
}