{
  "사건번호": "2010다19990",
  "소송당사자": "원고(상고인), 피고(피상고인) 주식회사 에이디티캡스",
  "소송 비용 청구": null,
  "전문 요약": "귀금속 가게와 경비회사 간 기계경비계약에서 금고감지기가 부착된 금고 내에 보관하지 않은 귀금속 도난 시 면책한다는 약관이 중요한 내용에 해당하므로 사업자는 고객에게 이를 명확히 설명할 의무가 있다. 또한 경비기기 작동불량으로 경보음이 울리지 않아 도난 피해가 발생한 경우, 경비기기 불량과 피해 사이에 인과관계가 인정될 수 있다. 원심은 이 점을 오해하여 판결에 잘못이 있어 파기환송되었다.",
  "기초 사실": "원고는 귀금속 가게를 운영하며 피고와 기계경비계약을 체결했고, 경비기기 작동불량으로 도난 피해가 발생했다.",
  "청구 취지": null,
  "원고 주장": "피고가 약관의 중요한 내용을 설명하지 않았고, 경비기기 작동불량과 도난 피해 사이에 인과관계가 있다고 주장했다.",
  "피고 주장": "면책약관은 업계에서 일반적이고, 원고가 충분히 인지할 수 있는 내용이므로 별도 설명의무가 없으며, 경비기기 불량과 피해 사이 인과관계도 없다고 주장했다.",
  "소결론": "면책약관은 중요한 내용에 해당하므로 설명의무가 있고, 경비기기 불량과 도난 피해 사이 인과관계가 인정될 수 있다.",
  "결론": "원심판결을 파기하고 사건을 서울고등법원에 환송한다."
}