{
  "사건번호": "2011다2517",
  "소송당사자": "원고(상고인), 피고(피상고인) 서윤종합건설 주식회사 외 14인",
  "소송 비용 청구": null,
  "전문 요약": "피고들은 공사대금 미지급 문제로 원고가 운영하는 예식장 앞에서 현수막, 피켓, 확성기, 장송곡 등으로 시위를 벌여 원고의 영업을 방해하고 모욕적 행위를 하였다. 원심은 피고들의 행위가 불법행위에 해당하지 않는다고 보았으나, 대법원은 시위의 경위와 절차를 감안하더라도 모욕 및 업무방해 행위가 정당행위에 해당하지 않으므로 불법행위가 성립한다고 판단했다. 다만, 원고가 주장한 재산상 손해는 인정할 증거가 부족하다고 보았으나, 정신적 손해에 대한 위자료 청구는 인정되어야 한다고 하여 원심의 위자료 부분을 파기하고 환송하였다.",
  "기초 사실": "피고들은 공사대금 미지급 문제로 원고가 임차한 예식장 앞에서 여러 차례 시위를 벌였고, 이 과정에서 모욕적 언행과 영업방해 행위가 있었다.",
  "청구 취지": "원고는 피고들의 불법시위로 인한 영업방해 및 명예훼손, 정신적 손해에 대한 손해배상을 청구하였다.",
  "원고 주장": "피고들이 예식장 앞에서 허위사실을 알리고 소란을 피워 영업을 방해하고 정신적 고통을 주었으므로 손해배상을 청구한다.",
  "피고 주장": "시위는 공사대금 미지급에 대한 권리행사의 일환으로 정당하며, 불법행위가 아니라고 주장하였다.",
  "소결론": "원심은 피고들의 행위가 불법행위에 해당하지 않는다고 보았으나, 대법원은 모욕 및 업무방해 행위가 정당행위에 해당하지 않으므로 불법행위가 성립한다고 판단하였다.",
  "결론": "원심판결 중 위자료 부분을 파기하고 환송, 나머지 상고는 기각하였다."
}