{
  "사건번호": "97가합3605",
  "소송당사자": "원고: 망 강영구의 소송수계인 강진모 외 3인(강이구, 강우석, 강진모, 강선영), 피고: 삼부아파트주민자치회 간부들(피고1, 피고2, 피고3)",
  "소송 비용 청구": "소송비용은 4분하여 3은 원고, 1은 피고가 부담",
  "전문 요약": "아파트 주민자치회 간부들이 자신들의 부당한 요구를 관철하기 위해 집단 민원을 제기하고, 물리력으로 인근 신축 건물의 공사를 방해하여 건물의 설계변경허가 및 준공이 지연되었다. 법원은 이로 인해 건축주들이 입은 손해에 대해 주민자치회 간부들의 공동불법행위 책임을 인정하여 손해배상 및 위자료 지급을 명령하였다.",
  "기초 사실": "원고들은 신축 건물의 건축주들이고, 피고들은 인근 아파트 주민자치회 간부들이다. 피고들은 집단 민원과 물리력으로 공사를 방해하였고, 이로 인해 공사 및 준공이 지연되었다.",
  "청구 취지": "피고들은 연대하여 원고들에게 각 손해배상금 및 지연손해금을 지급하라.",
  "원고 주장": "피고들의 공사방해로 인해 공사 지연 및 임대수입 손실 등 손해를 입었으므로 손해배상을 청구한다.",
  "피고 주장": "공사방해는 아파트 주민들의 권리 보호를 위한 정당한 행위이며, 손해배상 책임은 자치회에 있다.",
  "소결론": "피고들의 공사방해는 정당한 권리행사로 볼 수 없고, 자치회 외에 피고 개인에게도 불법행위 책임이 있다.",
  "결론": "피고들은 연대하여 원고들에게 손해배상 및 위자료를 지급할 의무가 있다. 나머지 청구는 기각한다."
}